props_ai/__init__.py
props_ai/hello.py
props_ai/props.py
props_ai-0.0.9.dist-info/LICENSE
props_ai-0.0.9.dist-info/METADATA
props_ai-0.0.9.dist-info/WHEEL
props_ai-0.0.9.dist-info/top_level.txt
props_ai-0.0.9.dist-info/RECORD
