Metadata-Version: 2.1
Name: props-ai
Version: 0.0.9
Summary: Props AI Python API Library
Home-page: https://github.com/PropsAI/propsai-python
Author: Props AI
Author-email: contact@getprops.ai
Keywords: openai,open,ai,gpt-3,gpt3,gpt4,propsai,observability,evaluation,analytics,experimentation
Classifier: Programming Language :: Python :: 3
Classifier: License :: OSI Approved :: MIT License
Classifier: Operating System :: OS Independent
License-File: LICENSE
Requires-Dist: requests >=2.0.0
